test/__init__.py
test/test_env_vars_data.py
wells_data_pipeline_cores/__init__.py
wells_data_pipeline_cores/common.py
wells_data_pipeline_cores/commons/__init__.py
wells_data_pipeline_cores/commons/dev_utils.py
wells_data_pipeline_cores/commons/env_variables.py
wells_data_pipeline_cores/commons/key_vaults.py
wells_data_pipeline_cores/commons/utils.py
wells_data_pipeline_cores/services/__init__.py
wells_data_pipeline_cores/services/adx/__init__.py
wells_data_pipeline_cores/services/adx/az_adx_data_service.py
wells_data_pipeline_cores/services/caches/__init__.py
wells_data_pipeline_cores/services/caches/keys/__init__.py
wells_data_pipeline_cores/services/caches/keys/dataset_key_info.py
wells_data_pipeline_cores/services/caches/keys/key_info.py
wells_data_pipeline_cores/services/caches/keys/sys_settings_key.py
wells_data_pipeline_cores/services/cores/__init__.py
wells_data_pipeline_cores/services/cores/az_ad_authz_service.py
wells_data_pipeline_cores/services/cores/az_storage_account_service.py
wells_data_pipeline_cores/services/cores/send_email_service.py
wells_data_pipeline_cores/services/cosmos/__init__.py
wells_data_pipeline_cores/services/cosmos/az_cosmos_data_service.py
wells_data_pipeline_cores/services/curation/__init__.py
wells_data_pipeline_cores/services/curation/curation_service.py
wells_data_pipeline_cores/services/dbx/__init__.py
wells_data_pipeline_cores/services/dbx/dbx_token_services.py
wells_data_pipeline_cores/services/etl/__init__.py
wells_data_pipeline_cores/services/etl/wells_etl_service.py
wells_data_pipeline_cores/services/snow/__init__.py
wells_data_pipeline_cores/services/snow/snow_data_service.py
wells_data_pipeline_cores/services/spark/__init__.py
wells_data_pipeline_cores/services/spark/spark_data_service.py
wells_data_pipeline_cores/services/wellview/__init__.py
wells_data_pipeline_cores-0.2.0.dist-info/METADATA
wells_data_pipeline_cores-0.2.0.dist-info/WHEEL
wells_data_pipeline_cores-0.2.0.dist-info/top_level.txt
wells_data_pipeline_cores-0.2.0.dist-info/RECORD
